prepgem/__init__.py
prepgem/prepgem.py
prepgem/preprocessing.py
prepgem/utils.py
PrepGem-1.0.6.dist-info/METADATA
PrepGem-1.0.6.dist-info/WHEEL
PrepGem-1.0.6.dist-info/top_level.txt
PrepGem-1.0.6.dist-info/RECORD
