Metadata-Version: 2.1
Name: PrepGem
Version: 1.0.6
Summary: Text Preprocessing package for NLP projects
Home-page: https://github.com/simoderyouch
Author: Mohamed Edderyouch
Author-email: mohamededderyouch5@gmail.com
Maintainer: Zineb Boughedda
License: Academic Free License
Classifier: Programming Language :: Python :: 3
Classifier: License :: OSI Approved :: MIT License
Classifier: Operating System :: OS Independent
Requires-Python: >=3.6
Requires-Dist: nltk
Requires-Dist: pandas
Requires-Dist: tqdm
Requires-Dist: SpellChecker
Requires-Dist: IPython
Requires-Dist: textblob
